README.rst
setup.py
Proxies/Proxies.py
Proxies/__init__.py
proxies.egg-info/PKG-INFO
proxies.egg-info/SOURCES.txt
proxies.egg-info/dependency_links.txt
proxies.egg-info/requires.txt
proxies.egg-info/top_level.txt