Metadata-Version: 1.1
Name: proxies
Version: 1.6
Summary: Get latest http proxies.
Home-page: https://github.com/MyFaith/proxies
Author: MyFaith
Author-email: faith0725@outlook.com
License: MIT
Keywords: proxy,proxies,requests
Platform: UNKNOWN
Classifier: Development Status :: 3 - Alpha
Classifier: Intended Audience :: Developers
Classifier: Topic :: Software Development :: Libraries :: Python Modules
Classifier: License :: OSI Approved :: MIT License
Classifier: Programming Language :: Python :: 3
Classifier: Programming Language :: Python :: 3.3
Classifier: Programming Language :: Python :: 3.4
Classifier: Programming Language :: Python :: 3.5
